nco/fifobuf.vhdl
---------------------------------------------------------------------

-- file: fifobuf.vhd
-- content: first-in first-out buffer 1 bit size
-- Created: 2020 august 14
-- Author: Roch Schanen
-- comments:
-- synchronous with the rising edge of trigger signal t
-- asynchronously cleared when reset signal r is low
-- generic size is any positive integer
-- size = 0 means that the pipe is a single wire
-- size = 1 means that the pipe is a single flip-flop
-- size = N means a linked chain of N flip-flops

---------------------------------------------------------------------

-------------------------------------------------
--                FIFOBUF
-------------------------------------------------

library ieee;
use ieee.std_logic_1164.all;

-------------------------------------------------

entity fifobuf is
    generic (size : integer := 0);  -- buffer size
    port (r : in  std_logic;        -- reset (active low)
          t : in  std_logic;        -- trigger (rising edge)
          i : in  std_logic;        -- data in
          o : out std_logic);       -- data out
end entity fifobuf;

-------------------------------------------------

architecture fifobuf_arch of fifobuf is
begin
    
    -- case N = 0:
    NOGATE : if size = 0 generate

    begin

        -- create a direct input-to-output link
        o <= i;

    end generate NOGATE;

    -- case N > 0:
    NGATES : if size > 0 generate

        -- buffer
        signal bf: std_logic_vector(size-1 downto 0);

    begin
        
        -- output most significant bit (MSB)
        o <= bf(size-1);

        -- sequential logic
        process(r, t)
        begin
        
            -- asynchronous reset
            if r = '0' then
                
                -- clear buffer
                bf <= (others => '0');

            -- synchronous shift
            elsif rising_edge(t) then
                
                -- shift (see note 1)
                for n in size-1 downto 1 loop
                    bf(n) <= bf(n-1);
                end loop;
                
                -- load least significant bit (LSB)
                bf(0) <= i;

            end if;

        end process;

    end generate NGATES;

-- done
end architecture fifobuf_arch;

-------------------------------------------------

-- note 1: intentionally, the shift loop does not generate
-- any logic when the generic size is equal to 1. in this
-- case, the buffer is  exactly bf(0). it has a size of 1.
-- it has input "i" and output "o".

nco/addsync.vhdl
---------------------------------------------------------------------

-- file: addsync.vhdl
-- content: full adder 1 bit size with sequential output
-- Created: 2020 august 14
-- Author: Roch Schanen
-- comments:
-- synchronous with the rising edge of trigger signal t
-- asynchronously cleared when reset signal r is low
-- with carry input and carry output logic

---------------------------------------------------------------------

-------------------------------------------------
--                ADD SYNC
-------------------------------------------------

library ieee;
use ieee.std_logic_1164.all;

-------------------------------------------------

entity addsync is
    port (r : in  std_logic;        -- reset (active low)
          t : in  std_logic;        -- trigger (rising edge)
          a, b, c : in  std_logic;  -- a, b and carry in
          s, o    : out std_logic); -- sum and carry out
end entity addsync;

-------------------------------------------------

architecture addsync_arch of addsync is

    -- combinational signals
    signal ss, oo : std_logic;

begin
    
    -- combinational logic
    ss <= a XOR b XOR c;
    oo <= (a AND b) OR (a AND c) OR (b AND c);
    
    -- sequential logic
    process (r, t)
    begin

        -- asynchronous reset
        if r = '0' then
            s <= '0';
            o <= '0';

        -- synchronous sum and carry out
        elsif rising_edge(t) then
            s <= ss;
            o <= oo;

        end if;

    end process;

-- done    
end architecture addsync_arch;

-------------------------------------------------

nco/plcnt.vhdl
---------------------------------------------------------------------

-- file: plcnt.vhdl
-- content: pipelined counter of arbitrary size
-- Created: 2020 september 02
-- Author: Roch Schanen
-- comments:
-- synchronous with the rising edge of trigger signal t
-- asynchronously cleared when reset signal r is low

---------------------------------------------------------------------

-------------------------------------------------
--                PIPELINED COUNTER
-------------------------------------------------

library ieee;
use ieee.std_logic_1164.all;

library work;
use work.all;

-------------------------------------------------

entity plcnt is
    generic (size : integer := 4); -- counter size
    port (r : in  std_logic;       -- reset (active low)
          t : in  std_logic;       -- trigger (rising edge)
          i : in  std_logic;       -- enable counter (carry in)
          o : out std_logic_vector(size-1 downto 0);
          c : out std_logic);      -- overload (carry out)
end entity plcnt;

-------------------------------------------------

architecture plcnt_arch of plcnt is

    -- signals
    signal cc : std_logic_vector(size   downto 0); -- carry lines
    signal oo : std_logic_vector(size-1 downto 0); -- adders ouput

begin

    -- count enable
    cc(0) <= i;

    -- for each data bit: 
    --   . one adder 
    --   . one output pipeline

    NETWORK : for n in 0 to size-1 generate

        add : entity addsync
            port map (r, t, '0', oo(n), cc(n), oo(n), cc(n+1));

        opl : entity fifobuf
            generic map (size-n)
            port map (r, t, oo(n), o(n));

    end generate NETWORK;

    -- set overload flag (carry out)
    c <= cc(size);

end architecture plcnt_arch;

-------------------------------------------------

benchreset.vhdl
---------------------------------------------------------------------

-- file: benchreset.vhdl
-- content: reset switch to be used by the fpga_bench
-- Created: 2024 july 28
-- Author: Roch Schanen
-- comments:
-- Simulate an external reset switch for the FPGA bench.
-- The reset start at a low level and rise after a fixed
-- PERIOD of time and remains high indefinitely (note that
-- this is a purely virtual device).

---------------------------------------------------------------------

-------------------------------------------------
--                BENCHRESET
-------------------------------------------------

library IEEE;
use IEEE.STD_LOGIC_1164.ALL;

entity benchreset is

    -- configure reset
    generic (PERIOD: time := 10 ns);

    -- only one output port
    Port ( o : out STD_LOGIC);

-- done
end benchreset;

architecture benchreset_arch of benchreset is

    -- define reset state
    --signal s : STD_LOGIC := '0';
    signal s : STD_LOGIC;

begin

    process

    begin

        wait for 1 ns;

        -- set reset state low
        s <= '0';

        -- wait
        wait for PERIOD;

        -- set reset state high
        s <= '1';

        -- wait forever
        wait;

    end process;

    -- output the reset state
    o <= s;

-- done
end benchreset_arch;

bench/benchclock.vhdl
---------------------------------------------------------------------

-- file: benchclock.vhd
-- content: clock to be used by the fpga_bench
-- Created: 2024 july 28
-- Author: Roch Schanen
-- comments:
-- Simulate an external clock for the FPGA bench.
-- The clock alternates state between 0 and 1. It
-- waits HALF_PERIOD between states, and repeats
-- indefinitely (note that this is a purely virtual
-- device).

---------------------------------------------------------------------

-------------------------------------------------
--                BENCH CLOCK
-------------------------------------------------

library IEEE;
use IEEE.STD_LOGIC_1164.ALL;

-------------------------------------------------

entity benchclock is

    -- configure clock
    generic (HALF_PERIOD: time := 5 ns);

    -- only one output port
    Port ( o : out STD_LOGIC);

-- done
end benchclock;

-------------------------------------------------

architecture benchclock_arch of benchclock is

    -- define clock state
    signal s : STD_LOGIC := '0';

begin

    process

    begin

        -- repeat indefinitely
        while true loop

            -- set clock state high
            s <= '1';

            -- wait
            wait for HALF_PERIOD;

            -- set clock state low
            s <= '0';

            -- wait
            wait for HALF_PERIOD;

        -- and again
        end loop;

    end process;

    -- output the clock state
    o <= s;

-- done
end benchclock_arch;

-------------------------------------------------

fpga_bench.vhdl
---------------------------------------------------------------------

-- file: fpga_bench.vhd
-- content: bench to simulate fpga code
-- Created: 2024 july 28
-- Author: Roch Schanen
-- comments:

---------------------------------------------------------------------

-------------------------------------------------
--                FPGA BENCH
-------------------------------------------------

library IEEE;
use IEEE.STD_LOGIC_1164.ALL;

library work;
use work.all;

-------------------------------------------------

entity fpga_bench is
end fpga_bench;

-------------------------------------------------

architecture fpga_bench_arch of fpga_bench is

    -- configuration
    constant SIZE : integer := 4;
    
    -- signals
    signal r : std_logic; -- reset
    signal c : std_logic; -- clock
    signal q : std_logic_vector(SIZE-1 downto 0); -- value
    signal o : std_logic; -- carry

begin

    -- instanciate bench clock
    bench_clock_1: entity benchclock
        generic map(2.5 ns) -- 200MHz
        port map(c);

    -- instanciate bench reset
    bench_reset_1: entity benchreset
        generic map(5 ns)
        port map(r);

    -- instanciate pipelined counter
    pl_cnt_1: entity plcnt
        generic map(SIZE)
        port map(r, c, '1', q, o);

end fpga_bench_arch;

-------------------------------------------------

fpga_bench.vcd
$date
  Mon Jul 29 11:12:06 2024
$end
$version
  GHDL v0
$end
$timescale
  1 fs
$end
$scope module standard $end
$upscope $end
$scope module std_logic_1164 $end
$upscope $end
$scope module fpga_bench $end
$var reg 1 ! r $end
$var reg 1 " c $end
$var reg 4 # q[3:0] $end
$var reg 1 $ o $end
$scope module bench_clock_1 $end
$var reg 1 % o $end
$var reg 1 & s $end
$upscope $end
$scope module bench_reset_1 $end
$var reg 1 ' o $end
$var reg 1 ( s $end
$upscope $end
$scope module pl_cnt_1 $end
$var reg 1 ) r $end
$var reg 1 * t $end
$var reg 1 + i $end
$var reg 4 , o[3:0] $end
$var reg 1 - c $end
$var reg 5 . cc[4:0] $end
$var reg 4 / oo[3:0] $end
$scope module network(0) $end
$scope module add $end
$var reg 1 0 r $end
$var reg 1 1 t $end
$var reg 1 2 a $end
$var reg 1 3 b $end
$var reg 1 4 c $end
$var reg 1 5 s $end
$var reg 1 6 o $end
$var reg 1 7 ss $end
$var reg 1 8 oo $end
$upscope $end
$scope module opl $end
$var reg 1 9 r $end
$var reg 1 : t $end
$var reg 1 ; i $end
$var reg 1 < o $end
$scope module ngates $end
$var reg 4 = bf[3:0] $end
$upscope $end
$upscope $end
$upscope $end
$scope module network(1) $end
$scope module add $end
$var reg 1 > r $end
$var reg 1 ? t $end
$var reg 1 @ a $end
$var reg 1 A b $end
$var reg 1 B c $end
$var reg 1 C s $end
$var reg 1 D o $end
$var reg 1 E ss $end
$var reg 1 F oo $end
$upscope $end
$scope module opl $end
$var reg 1 G r $end
$var reg 1 H t $end
$var reg 1 I i $end
$var reg 1 J o $end
$scope module ngates $end
$var reg 3 K bf[2:0] $end
$upscope $end
$upscope $end
$upscope $end
$scope module network(2) $end
$scope module add $end
$var reg 1 L r $end
$var reg 1 M t $end
$var reg 1 N a $end
$var reg 1 O b $end
$var reg 1 P c $end
$var reg 1 Q s $end
$var reg 1 R o $end
$var reg 1 S ss $end
$var reg 1 T oo $end
$upscope $end
$scope module opl $end
$var reg 1 U r $end
$var reg 1 V t $end
$var reg 1 W i $end
$var reg 1 X o $end
$scope module ngates $end
$var reg 2 Y bf[1:0] $end
$upscope $end
$upscope $end
$upscope $end
$scope module network(3) $end
$scope module add $end
$var reg 1 Z r $end
$var reg 1 [ t $end
$var reg 1 \ a $end
$var reg 1 ] b $end
$var reg 1 ^ c $end
$var reg 1 _ s $end
$var reg 1 ` o $end
$var reg 1 a ss $end
$var reg 1 b oo $end
$upscope $end
$scope module opl $end
$var reg 1 c r $end
$var reg 1 d t $end
$var reg 1 e i $end
$var reg 1 f o $end
$scope module ngates $end
$var reg 1 g bf[0:0] $end
$upscope $end
$upscope $end
$upscope $end
$upscope $end
$upscope $end
$enddefinitions $end
#0
U!
1"
bUUUU #
U$
1%
1&
U'
U(
U)
1*
1+
bUUUU ,
U-
bUUUU1 .
bUUUU /
U0
11
02
U3
14
U5
U6
U7
U8
U9
1:
U;
U<
bUUUU =
U>
1?
0@
UA
UB
UC
UD
UE
UF
UG
1H
UI
UJ
bUUU K
UL
1M
0N
UO
UP
UQ
UR
US
UT
UU
1V
UW
UX
bUU Y
UZ
1[
0\
U]
U^
U_
U`
Ua
Ub
Uc
1d
Ue
Uf
bU g
#1000000
0!
b0000 #
0$
0'
0(
0)
b0000 ,
0-
b00001 .
b0000 /
00
03
05
06
17
08
09
0;
0<
b0000 =
0>
0A
0B
0C
0D
0E
0F
0G
0I
0J
b000 K
0L
0O
0P
0Q
0R
0S
0T
0U
0W
0X
b00 Y
0Z
0]
0^
0_
0`
0a
0b
0c
0e
0f
b0 g
#2500000
0"
0%
0&
0*
01
0:
0?
0H
0M
0V
0[
0d
#5000000
1"
1%
1&
1*
11
1:
1?
1H
1M
1V
1[
1d
#6000000
1!
1'
1(
1)
10
19
1>
1G
1L
1U
1Z
1c
#7500000
0"
0%
0&
0*
01
0:
0?
0H
0M
0V
0[
0d
#10000000
1"
1%
1&
1*
b0001 /
11
13
15
07
18
1:
1;
1?
1H
1M
1V
1[
1d
#12500000
0"
0%
0&
0*
01
0:
0?
0H
0M
0V
0[
0d
#15000000
1"
1%
1&
1*
b00011 .
b0000 /
11
03
05
16
17
08
1:
0;
b0001 =
1?
1B
1E
1H
1M
1V
1[
1d
#17500000
0"
0%
0&
0*
01
0:
0?
0H
0M
0V
0[
0d
#20000000
1"
1%
1&
1*
b00001 .
b0011 /
11
13
15
06
07
18
1:
1;
b0010 =
1?
1A
0B
1C
1H
1I
1M
1V
1[
1d
#22500000
0"
0%
0&
0*
01
0:
0?
0H
0M
0V
0[
0d
#25000000
1"
1%
1&
1*
b00011 .
b0010 /
11
03
05
16
17
08
1:
0;
b0101 =
1?
1B
0E
1F
1H
b001 K
1M
1V
1[
1d
#27500000
0"
0%
0&
0*
01
0:
0?
0H
0M
0V
0[
0d
#30000000
1"
b0001 #
1%
1&
1*
b0001 ,
b00101 .
b0001 /
11
13
15
06
07
18
1:
1;
1<
b1010 =
1?
0A
0B
0C
1D
0F
1H
0I
b011 K
1M
1P
1S
1V
1[
1d
#32500000
0"
0%
0&
0*
01
0:
0?
0H
0M
0V
0[
0d
#35000000
1"
b0010 #
1%
1&
1*
b0010 ,
b00011 .
b0100 /
11
03
05
16
17
08
1:
0;
0<
b0101 =
1?
1B
0D
1E
1H
1J
b110 K
1M
1O
0P
1Q
1V
1W
1[
1d
#37500000
0"
0%
0&
0*
01
0:
0?
0H
0M
0V
0[
0d
#40000000
1"
b0011 #
1%
1&
1*
b0011 ,
b00001 .
b0111 /
11
13
15
06
07
18
1:
1;
1<
b1010 =
1?
1A
0B
1C
1H
1I
b100 K
1M
1V
b01 Y
1[
1d
#42500000
0"
0%
0&
0*
01
0:
0?
0H
0M
0V
0[
0d
#45000000
1"
b0100 #
1%
1&
1*
b0100 ,
b00011 .
b0110 /
11
03
05
16
17
08
1:
0;
0<
b0101 =
1?
1B
0E
1F
1H
0J
b001 K
1M
1V
1X
b11 Y
1[
1d
#47500000
0"
0%
0&
0*
01
0:
0?
0H
0M
0V
0[
0d
#50000000
1"
b0101 #
1%
1&
1*
b0101 ,
b00101 .
b0101 /
11
13
15
06
07
18
1:
1;
1<
b1010 =
1?
0A
0B
0C
1D
0F
1H
0I
b011 K
1M
1P
0S
1T
1V
1[
1d
#52500000
0"
0%
0&
0*
01
0:
0?
0H
0M
0V
0[
0d
#55000000
1"
b0110 #
1%
1&
1*
b0110 ,
b01011 .
b0000 /
11
03
05
16
17
08
1:
0;
0<
b0101 =
1?
1B
0D
1E
1H
1J
b110 K
1M
0O
0P
0Q
1R
0T
1V
0W
1[
1^
1a
1d
#57500000
0"
0%
0&
0*
01
0:
0?
0H
0M
0V
0[
0d
#60000000
1"
b0111 #
1%
1&
1*
b0111 ,
b00001 .
b1011 /
11
13
15
06
07
18
1:
1;
1<
b1010 =
1?
1A
0B
1C
1H
1I
b100 K
1M
0R
1V
b10 Y
1[
1]
0^
1_
1d
1e
#62500000
0"
0%
0&
0*
01
0:
0?
0H
0M
0V
0[
0d
#65000000
1"
b1000 #
1%
1&
1*
b1000 ,
b00011 .
b1010 /
11
03
05
16
17
08
1:
0;
0<
b0101 =
1?
1B
0E
1F
1H
0J
b001 K
1M
1V
0X
b00 Y
1[
1d
1f
b1 g
#67500000
0"
0%
0&
0*
01
0:
0?
0H
0M
0V
0[
0d
#70000000
1"
b1001 #
1%
1&
1*
b1001 ,
b00101 .
b1001 /
11
13
15
06
07
18
1:
1;
1<
b1010 =
1?
0A
0B
0C
1D
0F
1H
0I
b011 K
1M
1P
1S
1V
1[
1d
#72500000
0"
0%
0&
0*
01
0:
0?
0H
0M
0V
0[
0d
#75000000
1"
b1010 #
1%
1&
1*
b1010 ,
b00011 .
b1100 /
11
03
05
16
17
08
1:
0;
0<
b0101 =
1?
1B
0D
1E
1H
1J
b110 K
1M
1O
0P
1Q
1V
1W
1[
1d
#77500000
0"
0%
0&
0*
01
0:
0?
0H
0M
0V
0[
0d
#80000000
1"
b1011 #
1%
1&
1*
b1011 ,
b00001 .
b1111 /
11
13
15
06
07
18
1:
1;
1<
b1010 =
1?
1A
0B
1C
1H
1I
b100 K
1M
1V
b01 Y
1[
1d
#82500000
0"
0%
0&
0*
01
0:
0?
0H
0M
0V
0[
0d
#85000000
1"
b1100 #
1%
1&
1*
b1100 ,
b00011 .
b1110 /
11
03
05
16
17
08
1:
0;
0<
b0101 =
1?
1B
0E
1F
1H
0J
b001 K
1M
1V
1X
b11 Y
1[
1d
#87500000
0"
0%
0&
0*
01
0:
0?
0H
0M
0V
0[
0d
#90000000
1"
b1101 #
1%
1&
1*
b1101 ,
b00101 .
b1101 /
11
13
15
06
07
18
1:
1;
1<
b1010 =
1?
0A
0B
0C
1D
0F
1H
0I
b011 K
1M
1P
0S
1T
1V
1[
1d
#92500000
0"
0%
0&
0*
01
0:
0?
0H
0M
0V
0[
0d
#95000000
1"
b1110 #
1%
1&
1*
b1110 ,
b01011 .
b1000 /
11
03
05
16
17
08
1:
0;
0<
b0101 =
1?
1B
0D
1E
1H
1J
b110 K
1M
0O
0P
0Q
1R
0T
1V
0W
1[
1^
0a
1b
1d
#97500000
0"
0%
0&
0*
01
0:
0?
0H
0M
0V
0[
0d
#100000000
1"
b1111 #
1$
1%
1&
1*
b1111 ,
1-
b10001 .
b0011 /
11
13
15
06
07
18
1:
1;
1<
b1010 =
1?
1A
0B
1C
1H
1I
b100 K
1M
0R
1V
b10 Y
1[
0]
0^
0_
1`
0b
1d
0e
#102500000
0"
0%
0&
0*
01
0:
0?
0H
0M
0V
0[
0d
#105000000
1"
b0000 #
0$
1%
1&
1*
b0000 ,
0-
b00011 .
b0010 /
11
03
05
16
17
08
1:
0;
0<
b0101 =
1?
1B
0E
1F
1H
0J
b001 K
1M
1V
0X
b00 Y
1[
0`
1d
0f
b0 g
#107500000
0"
0%
0&
0*
01
0:
0?
0H
0M
0V
0[
0d
#110000000
1"
b0001 #
1%
1&
1*
b0001 ,
b00101 .
b0001 /
11
13
15
06
07
18
1:
1;
1<
b1010 =
1?
0A
0B
0C
1D
0F
1H
0I
b011 K
1M
1P
1S
1V
1[
1d
#112500000
0"
0%
0&
0*
01
0:
0?
0H
0M
0V
0[
0d
#115000000
1"
b0010 #
1%
1&
1*
b0010 ,
b00011 .
b0100 /
11
03
05
16
17
08
1:
0;
0<
b0101 =
1?
1B
0D
1E
1H
1J
b110 K
1M
1O
0P
1Q
1V
1W
1[
1d
#117500000
0"
0%
0&
0*
01
0:
0?
0H
0M
0V
0[
0d
#120000000
1"
b0011 #
1%
1&
1*
b0011 ,
b00001 .
b0111 /
11
13
15
06
07
18
1:
1;
1<
b1010 =
1?
1A
0B
1C
1H
1I
b100 K
1M
1V
b01 Y
1[
1d
#122500000
0"
0%
0&
0*
01
0:
0?
0H
0M
0V
0[
0d
#125000000
1"
b0100 #
1%
1&
1*
b0100 ,
b00011 .
b0110 /
11
03
05
16
17
08
1:
0;
0<
b0101 =
1?
1B
0E
1F
1H
0J
b001 K
1M
1V
1X
b11 Y
1[
1d
#127500000
0"
0%
0&
0*
01
0:
0?
0H
0M
0V
0[
0d
#130000000
1"
b0101 #
1%
1&
1*
b0101 ,
b00101 .
b0101 /
11
13
15
06
07
18
1:
1;
1<
b1010 =
1?
0A
0B
0C
1D
0F
1H
0I
b011 K
1M
1P
0S
1T
1V
1[
1d
#132500000
0"
0%
0&
0*
01
0:
0?
0H
0M
0V
0[
0d
#135000000
1"
b0110 #
1%
1&
1*
b0110 ,
b01011 .
b0000 /
11
03
05
16
17
08
1:
0;
0<
b0101 =
1?
1B
0D
1E
1H
1J
b110 K
1M
0O
0P
0Q
1R
0T
1V
0W
1[
1^
1a
1d
#137500000
0"
0%
0&
0*
01
0:
0?
0H
0M
0V
0[
0d
#140000000
1"
b0111 #
1%
1&
1*
b0111 ,
b00001 .
b1011 /
11
13
15
06
07
18
1:
1;
1<
b1010 =
1?
1A
0B
1C
1H
1I
b100 K
1M
0R
1V
b10 Y
1[
1]
0^
1_
1d
1e
#142500000
0"
0%
0&
0*
01
0:
0?
0H
0M
0V
0[
0d
#145000000
1"
b1000 #
1%
1&
1*
b1000 ,
b00011 .
b1010 /
11
03
05
16
17
08
1:
0;
0<
b0101 =
1?
1B
0E
1F
1H
0J
b001 K
1M
1V
0X
b00 Y
1[
1d
1f
b1 g
#147500000
0"
0%
0&
0*
01
0:
0?
0H
0M
0V
0[
0d
#150000000
1"
b1001 #
1%
1&
1*
b1001 ,
b00101 .
b1001 /
11
13
15
06
07
18
1:
1;
1<
b1010 =
1?
0A
0B
0C
1D
0F
1H
0I
b011 K
1M
1P
1S
1V
1[
1d
#152500000
0"
0%
0&
0*
01
0:
0?
0H
0M
0V
0[
0d
#155000000
1"
b1010 #
1%
1&
1*
b1010 ,
b00011 .
b1100 /
11
03
05
16
17
08
1:
0;
0<
b0101 =
1?
1B
0D
1E
1H
1J
b110 K
1M
1O
0P
1Q
1V
1W
1[
1d
#157500000
0"
0%
0&
0*
01
0:
0?
0H
0M
0V
0[
0d
#160000000
1"
b1011 #
1%
1&
1*
b1011 ,
b00001 .
b1111 /
11
13
15
06
07
18
1:
1;
1<
b1010 =
1?
1A
0B
1C
1H
1I
b100 K
1M
1V
b01 Y
1[
1d
#162500000
0"
0%
0&
0*
01
0:
0?
0H
0M
0V
0[
0d
#165000000
1"
b1100 #
1%
1&
1*
b1100 ,
b00011 .
b1110 /
11
03
05
16
17
08
1:
0;
0<
b0101 =
1?
1B
0E
1F
1H
0J
b001 K
1M
1V
1X
b11 Y
1[
1d
#167500000
0"
0%
0&
0*
01
0:
0?
0H
0M
0V
0[
0d
#170000000
1"
b1101 #
1%
1&
1*
b1101 ,
b00101 .
b1101 /
11
13
15
06
07
18
1:
1;
1<
b1010 =
1?
0A
0B
0C
1D
0F
1H
0I
b011 K
1M
1P
0S
1T
1V
1[
1d
#172500000
0"
0%
0&
0*
01
0:
0?
0H
0M
0V
0[
0d
#175000000
1"
b1110 #
1%
1&
1*
b1110 ,
b01011 .
b1000 /
11
03
05
16
17
08
1:
0;
0<
b0101 =
1?
1B
0D
1E
1H
1J
b110 K
1M
0O
0P
0Q
1R
0T
1V
0W
1[
1^
0a
1b
1d
#177500000
0"
0%
0&
0*
01
0:
0?
0H
0M
0V
0[
0d
#180000000
1"
b1111 #
1$
1%
1&
1*
b1111 ,
1-
b10001 .
b0011 /
11
13
15
06
07
18
1:
1;
1<
b1010 =
1?
1A
0B
1C
1H
1I
b100 K
1M
0R
1V
b10 Y
1[
0]
0^
0_
1`
0b
1d
0e
#182500000
0"
0%
0&
0*
01
0:
0?
0H
0M
0V
0[
0d
#185000000
1"
b0000 #
0$
1%
1&
1*
b0000 ,
0-
b00011 .
b0010 /
11
03
05
16
17
08
1:
0;
0<
b0101 =
1?
1B
0E
1F
1H
0J
b001 K
1M
1V
0X
b00 Y
1[
0`
1d
0f
b0 g
#187500000
0"
0%
0&
0*
01
0:
0?
0H
0M
0V
0[
0d
#190000000
1"
b0001 #
1%
1&
1*
b0001 ,
b00101 .
b0001 /
11
13
15
06
07
18
1:
1;
1<
b1010 =
1?
0A
0B
0C
1D
0F
1H
0I
b011 K
1M
1P
1S
1V
1[
1d
#192500000
0"
0%
0&
0*
01
0:
0?
0H
0M
0V
0[
0d
#195000000
1"
b0010 #
1%
1&
1*
b0010 ,
b00011 .
b0100 /
11
03
05
16
17
08
1:
0;
0<
b0101 =
1?
1B
0D
1E
1H
1J
b110 K
1M
1O
0P
1Q
1V
1W
1[
1d
#197500000
0"
0%
0&
0*
01
0:
0?
0H
0M
0V
0[
0d
#200000000
1"
b0011 #
1%
1&
1*
b0011 ,
b00001 .
b0111 /
11
13
15
06
07
18
1:
1;
1<
b1010 =
1?
1A
0B
1C
1H
1I
b100 K
1M
1V
b01 Y
1[
1d
