bench/benchclock.vhdl
---------------------------------------------------------------------

-- file: benchclock.vhd
-- content: clock to be used by the fpga_bench
-- Created: 2024 july 28
-- Author: Roch Schanen
-- comments:
-- Simulate an external clock for the FPGA bench.
-- The clock alternates state between 0 and 1. It
-- waits HALF_PERIOD between states, and repeats
-- indefinitely (note that this is a purely virtual
-- device).

---------------------------------------------------------------------

-------------------------------------------------
--                BENCHCLOCK
-------------------------------------------------

library IEEE;
use IEEE.STD_LOGIC_1164.ALL;

entity benchclock is

    -- configure clock
    generic (HALF_PERIOD: time := 5 ns);

    -- only one output port
    Port ( o : out STD_LOGIC);

-- done
end benchclock;

architecture benchclock_arch of benchclock is

    -- define clock state
    signal s : STD_LOGIC := '0';

begin

    process

    begin

        -- repeat indefinitely
        while true loop

            -- set clock state high
            s <= '1';

            -- wait
            wait for HALF_PERIOD;

            -- set clock state low
            s <= '0';

            -- wait
            wait for HALF_PERIOD;

        -- and again
        end loop;

    end process;

    -- output the clock state
    o <= s;

-- done
end benchclock_arch;

fpga_bench.vhdl
---------------------------------------------------------------------

-- file: fpga_bench.vhd
-- content: bench to simulate fpga code
-- Created: 2024 july 28
-- Author: Roch Schanen
-- comments: simulate external clock, input and outputs ports.

---------------------------------------------------------------------

-------------------------------------------------
--                FPGA BENCH
-------------------------------------------------

library IEEE;
use IEEE.STD_LOGIC_1164.ALL;

library work;
use work.benchclock;

entity fpga_bench is
end fpga_bench;

architecture fpga_bench_arch of fpga_bench is

    -- signals

    signal c : std_logic;

begin

    -- instanciate benchclock

    bench_clock_1: entity benchclock
        generic map(2.5 ns) -- 200MHz
        port map(c);

end fpga_bench_arch;

fpga_bench.vcd
$date
  Sun Jul 28 21:27:25 2024
$end
$version
  GHDL v0
$end
$timescale
  1 fs
$end
$scope module standard $end
$upscope $end
$scope module std_logic_1164 $end
$upscope $end
$scope module fpga_bench $end
$var reg 1 ! c $end
$scope module bench_clock_1 $end
$var reg 1 " o $end
$var reg 1 # s $end
$upscope $end
$upscope $end
$enddefinitions $end
#0
1!
1"
1#
#2500000
0!
0"
0#
#5000000
1!
1"
1#
#7500000
0!
0"
0#
#10000000
1!
1"
1#
#12500000
0!
0"
0#
#15000000
1!
1"
1#
#17500000
0!
0"
0#
#20000000
1!
1"
1#
#22500000
0!
0"
0#
#25000000
1!
1"
1#
#27500000
0!
0"
0#
#30000000
1!
1"
1#
#32500000
0!
0"
0#
#35000000
1!
1"
1#
