nco/fifobuf.vhdl
---------------------------------------------------------------------

-- file: fifobuf.vhd
-- content: first-in first-out buffer 1 bit size
-- Created: 2020 august 14
-- Author: Roch Schanen
-- comments:
-- synchronous with the rising edge of trigger signal t
-- asynchronously cleared when reset signal r is low
-- generic size is any positive integer
-- size = 0 means that the pipe is a single wire
-- size = 1 means that the pipe is a single flip-flop
-- size = N means a linked chain of N flip-flops

---------------------------------------------------------------------

-------------------------------------------------
--                FIFOBUF
-------------------------------------------------

library ieee;
use ieee.std_logic_1164.all;

-------------------------------------------------

entity fifobuf is
    generic (size : integer := 0);  -- buffer size
    port (r : in  std_logic;        -- reset (active low)
          t : in  std_logic;        -- trigger (rising edge)
          i : in  std_logic;        -- data in
          o : out std_logic);       -- data out
end entity fifobuf;

-------------------------------------------------

architecture fifobuf_arch of fifobuf is
begin
    
    -- case N = 0:
    NOGATE : if size = 0 generate

    begin

        -- create a direct input-to-output link
        o <= i;

    end generate NOGATE;

    -- case N > 0:
    NGATES : if size > 0 generate

        -- buffer
        signal bf: std_logic_vector(size-1 downto 0);

    begin
        
        -- output most significant bit (MSB)
        o <= bf(size-1);

        -- sequential logic
        process(r, t)
        begin
        
            -- asynchronous reset
            if r = '0' then
                
                -- clear buffer
                bf <= (others => '0');

            -- synchronous shift
            elsif rising_edge(t) then
                
                -- shift (see note 1)
                for n in size-1 downto 1 loop
                    bf(n) <= bf(n-1);
                end loop;
                
                -- load least significant bit (LSB)
                bf(0) <= i;

            end if;

        end process;

    end generate NGATES;

-- done
end architecture fifobuf_arch;

-------------------------------------------------

-- note 1: intentionally, the shift loop does not generate
-- any logic when the generic size is equal to 1. in this
-- case, the buffer is  exactly bf(0). it has a size of 1.
-- it has input "i" and output "o".

benchreset.vhdl
---------------------------------------------------------------------

-- file: benchreset.vhdl
-- content: reset switch to be used by the fpga_bench
-- Created: 2024 july 28
-- Author: Roch Schanen
-- comments:
-- Simulate an external reset switch for the FPGA bench.
-- The reset start at a low level and rise after a fixed
-- PERIOD of time and remains high indefinitely (note that
-- this is a purely virtual device).

---------------------------------------------------------------------

-------------------------------------------------
--                BENCHRESET
-------------------------------------------------

library IEEE;
use IEEE.STD_LOGIC_1164.ALL;

entity benchreset is

    -- configure reset
    generic (PERIOD: time := 10 ns);

    -- only one output port
    Port ( o : out STD_LOGIC);

-- done
end benchreset;

architecture benchreset_arch of benchreset is

    -- define reset state
    --signal s : STD_LOGIC := '0';
    signal s : STD_LOGIC;

begin

    process

    begin

        wait for 1 ns;

        -- set reset state low
        s <= '0';

        -- wait
        wait for PERIOD;

        -- set reset state high
        s <= '1';

        -- wait forever
        wait;

    end process;

    -- output the reset state
    o <= s;

-- done
end benchreset_arch;

bench/benchclock.vhdl
---------------------------------------------------------------------

-- file: benchclock.vhd
-- content: clock to be used by the fpga_bench
-- Created: 2024 july 28
-- Author: Roch Schanen
-- comments:
-- Simulate an external clock for the FPGA bench.
-- The clock alternates state between 0 and 1. It
-- waits HALF_PERIOD between states, and repeats
-- indefinitely (note that this is a purely virtual
-- device).

---------------------------------------------------------------------

-------------------------------------------------
--                BENCHCLOCK
-------------------------------------------------

library IEEE;
use IEEE.STD_LOGIC_1164.ALL;

entity benchclock is

    -- configure clock
    generic (HALF_PERIOD: time := 5 ns);

    -- only one output port
    Port ( o : out STD_LOGIC);

-- done
end benchclock;

architecture benchclock_arch of benchclock is

    -- define clock state
    signal s : STD_LOGIC := '0';

begin

    process

    begin

        -- repeat indefinitely
        while true loop

            -- set clock state high
            s <= '1';

            -- wait
            wait for HALF_PERIOD;

            -- set clock state low
            s <= '0';

            -- wait
            wait for HALF_PERIOD;

        -- and again
        end loop;

    end process;

    -- output the clock state
    o <= s;

-- done
end benchclock_arch;

fpga_bench.vhdl
---------------------------------------------------------------------

-- file: fpga_bench.vhd
-- content: bench to simulate fpga code
-- Created: 2024 july 28
-- Author: Roch Schanen
-- comments:

---------------------------------------------------------------------

-------------------------------------------------
--                FPGA BENCH
-------------------------------------------------

library IEEE;
use IEEE.STD_LOGIC_1164.ALL;

library work;
use work.benchclock;
use work.benchreset;
use work.fifobuf;

entity fpga_bench is
end fpga_bench;

architecture fpga_bench_arch of fpga_bench is

    -- signals

    signal c : std_logic; -- clock
    signal o : std_logic; -- output
    signal r : std_logic; -- reset

begin

    -- instanciate benchclock

    bench_clock_1: entity benchclock
        generic map(2.5 ns) -- 200MHz
        port map(c);

    -- instanciate benchreset

    bench_reset_1: entity benchreset
        generic map(5 ns)
        port map(r);

    -- instanciate fifobuf

    fifo_buffer_1: entity fifobuf
        generic map (5)           -- five flip-flops
        port map (r, c, '1', o);  -- fixed input 1

end fpga_bench_arch;

fpga_bench.vcd
$date
  Mon Jul 29 07:56:13 2024
$end
$version
  GHDL v0
$end
$timescale
  1 fs
$end
$scope module standard $end
$upscope $end
$scope module std_logic_1164 $end
$upscope $end
$scope module fpga_bench $end
$var reg 1 ! c $end
$var reg 1 " o $end
$var reg 1 # r $end
$scope module bench_clock_1 $end
$var reg 1 $ o $end
$var reg 1 % s $end
$upscope $end
$scope module bench_reset_1 $end
$var reg 1 & o $end
$var reg 1 ' s $end
$upscope $end
$scope module fifo_buffer_1 $end
$var reg 1 ( r $end
$var reg 1 ) t $end
$var reg 1 * i $end
$var reg 1 + o $end
$scope module ngates $end
$var reg 5 , bf[4:0] $end
$upscope $end
$upscope $end
$upscope $end
$enddefinitions $end
#0
1!
U"
U#
1$
1%
U&
U'
U(
1)
1*
U+
bUUUU1 ,
#1000000
0"
0#
0&
0'
0(
0+
b00000 ,
#2500000
0!
0$
0%
0)
#5000000
1!
1$
1%
1)
#6000000
1#
1&
1'
1(
#7500000
0!
0$
0%
0)
#10000000
1!
1$
1%
1)
b00001 ,
#12500000
0!
0$
0%
0)
#15000000
1!
1$
1%
1)
b00011 ,
#17500000
0!
0$
0%
0)
#20000000
1!
1$
1%
1)
b00111 ,
#22500000
0!
0$
0%
0)
#25000000
1!
1$
1%
1)
b01111 ,
#27500000
0!
0$
0%
0)
#30000000
1!
1"
1$
1%
1)
1+
b11111 ,
#32500000
0!
0$
0%
0)
#35000000
1!
1$
1%
1)
#37500000
0!
0$
0%
0)
#40000000
1!
1$
1%
1)
#42500000
0!
0$
0%
0)
#45000000
1!
1$
1%
1)
#47500000
0!
0$
0%
0)
#50000000
1!
1$
1%
1)
