plpr/plpr.vhdl
---------------------------------------------------------------------

-- file: plpr.vhdl
-- content: pipelined product
-- Created: 2024 august 4
-- Author: Roch Schanen
-- comments:
-- synchronous with the rising edge of trigger signal t
-- asynchronously cleared when reset signal r is low
-- generic size has been tested for integers larger than 4      <- not yet
-- compute the product of two binary numbers

-- positively defined first
-- symmtric size to start, asymetric later

---------------------------------------------------------------------

-------------------------------------------------
--           PIPELINED PRODUCT ARITHMETIC
-------------------------------------------------

library ieee;
use ieee.std_logic_1164.all;

library work;
use work.all;

-------------------------------------------------

entity plpr is
    generic (size : integer := 4);                      -- factors size (4 x 4)
    port (r : in  std_logic;                            -- reset (active low)
          t : in  std_logic;                            -- trigger (rising edge)
          a : in  std_logic_vector(size-1 downto 0);    -- input A (4)
          b : in  std_logic_vector(size-1 downto 0);    -- input B (4)
          p : out std_logic_vector(2*size-1 downto 0)); -- product AB (8)
end entity plpr;

-------------------------------------------------

architecture plpr_arch of plpr is

begin

    process
    begin

        p <= "00000000";

        -- nothing 
        report "done";
        wait;

    end process;

end architecture plpr_arch;

-------------------------------------------------

benchreset.vhdl
---------------------------------------------------------------------

-- file: benchreset.vhdl
-- content: reset switch to be used by the fpga_bench
-- Created: 2024 july 28
-- Author: Roch Schanen
-- comments:
-- Simulate an external reset switch for the FPGA bench.
-- The reset start at a low level and rise after a fixed
-- PERIOD of time and remains high indefinitely (note that
-- this is a purely virtual device).

---------------------------------------------------------------------

-------------------------------------------------
--                BENCHRESET
-------------------------------------------------

library IEEE;
use IEEE.STD_LOGIC_1164.ALL;

entity benchreset is

    -- configure reset
    generic (PERIOD: time := 10 ns);

    -- only one output port
    Port ( o : out STD_LOGIC);

-- done
end benchreset;

architecture benchreset_arch of benchreset is

    -- define reset state
    --signal s : STD_LOGIC := '0';
    signal s : STD_LOGIC;

begin

    process

    begin

        wait for 1 ns;

        -- set reset state low
        s <= '0';

        -- wait
        wait for PERIOD;

        -- set reset state high
        s <= '1';

        -- wait forever
        wait;

    end process;

    -- output the reset state
    o <= s;

-- done
end benchreset_arch;

bench/benchclock.vhdl
---------------------------------------------------------------------

-- file: benchclock.vhd
-- content: clock to be used by the fpga_bench
-- Created: 2024 july 28
-- Author: Roch Schanen
-- comments:
-- Simulate an external clock for the FPGA bench.
-- The clock alternates state between 0 and 1. It
-- waits HALF_PERIOD between states, and repeats
-- indefinitely (note that this is a purely virtual
-- device).

---------------------------------------------------------------------

-------------------------------------------------
--                BENCHCLOCK
-------------------------------------------------

library IEEE;
use IEEE.STD_LOGIC_1164.ALL;

entity benchclock is

    -- configure clock
    generic (HALF_PERIOD: time := 5 ns);

    -- only one output port
    Port ( o : out STD_LOGIC);

-- done
end benchclock;

architecture benchclock_arch of benchclock is

    -- define clock state
    signal s : STD_LOGIC := '0';

begin

    process

    begin

        -- repeat indefinitely
        while true loop

            -- set clock state high
            s <= '1';

            -- wait
            wait for HALF_PERIOD;

            -- set clock state low
            s <= '0';

            -- wait
            wait for HALF_PERIOD;

        -- and again
        end loop;

    end process;

    -- output the clock state
    o <= s;

-- done
end benchclock_arch;

plpr_bench.vhdl
---------------------------------------------------------------------

-- file: plpr_bench.vhd
-- content: bench to simulate plpr code
-- Created: 2024 August 4
-- Author: Roch Schanen
-- comments:

---------------------------------------------------------------------

-------------------------------------------------
--          PIPELINED PRODUCT BENCH
-------------------------------------------------

library IEEE;
use IEEE.STD_LOGIC_1164.ALL;

library work;
use work.all;

-------------------------------------------------

entity plpr_bench is
end plpr_bench;

-------------------------------------------------

architecture plpr_bench_arch of plpr_bench is

    -- configuration

    constant FACTORSIZE : integer := 4;

    -- signals
    signal r : std_logic; -- reset
    signal c : std_logic; -- clock
    signal q : std_logic_vector(2*FACTORSIZE-1 downto 0); -- output

begin

    -- instanciate bench clock
    bench_clock_1: entity benchclock
        generic map(2.5 ns) -- 200MHz
        port map(c);

    -- instanciate bench reset
    bench_reset_1: entity benchreset
        generic map(3 ns)
        port map(r);

    -- instanciate pipelined nco
    pl_pr_1: entity plpr
        generic map(FACTORSIZE)
        port map(r, c, "0000", "0000", q);

end plpr_bench_arch;

-------------------------------------------------

.outputs/bench.vcd
$date
  Sun Aug  4 17:11:20 2024
$end
$version
  GHDL v0
$end
$timescale
  1 fs
$end
$scope module standard $end
$upscope $end
$scope module std_logic_1164 $end
$upscope $end
$scope module plpr_bench $end
$var reg 1 ! r $end
$var reg 1 " c $end
$var reg 8 # q[7:0] $end
$scope module bench_clock_1 $end
$var reg 1 $ o $end
$var reg 1 % s $end
$upscope $end
$scope module bench_reset_1 $end
$var reg 1 & o $end
$var reg 1 ' s $end
$upscope $end
$scope module pl_pr_1 $end
$var reg 1 ( r $end
$var reg 1 ) t $end
$var reg 4 * a[3:0] $end
$var reg 4 + b[3:0] $end
$var reg 8 , p[7:0] $end
$upscope $end
$upscope $end
$enddefinitions $end
#0
U!
1"
b00000000 #
1$
1%
U&
U'
U(
1)
b0000 *
b0000 +
b00000000 ,
#1000000
0!
0&
0'
0(
#2500000
0"
0$
0%
0)
#4000000
1!
1&
1'
1(
#5000000
1"
1$
1%
1)
#7500000
0"
0$
0%
0)
#10000000
1"
1$
1%
1)
#12500000
0"
0$
0%
0)
#15000000
1"
1$
1%
1)
#17500000
0"
0$
0%
0)
#20000000
1"
1$
1%
1)
#22500000
0"
0$
0%
0)
#25000000
1"
1$
1%
1)
#27500000
0"
0$
0%
0)
#30000000
1"
1$
1%
1)
#32500000
0"
0$
0%
0)
#35000000
1"
1$
1%
1)
#37500000
0"
0$
0%
0)
#40000000
1"
1$
1%
1)
#42500000
0"
0$
0%
0)
#45000000
1"
1$
1%
1)
#47500000
0"
0$
0%
0)
#50000000
1"
1$
1%
1)
#52500000
0"
0$
0%
0)
#55000000
1"
1$
1%
1)
#57500000
0"
0$
0%
0)
#60000000
1"
1$
1%
1)
#62500000
0"
0$
0%
0)
#65000000
1"
1$
1%
1)
#67500000
0"
0$
0%
0)
#70000000
1"
1$
1%
1)
#72500000
0"
0$
0%
0)
#75000000
1"
1$
1%
1)
#77500000
0"
0$
0%
0)
#80000000
1"
1$
1%
1)
#82500000
0"
0$
0%
0)
#85000000
1"
1$
1%
1)
#87500000
0"
0$
0%
0)
#90000000
1"
1$
1%
1)
#92500000
0"
0$
0%
0)
#95000000
1"
1$
1%
1)
#97500000
0"
0$
0%
0)
#100000000
1"
1$
1%
1)
