plpr/fifostream.vhdl
-------------------------------------------------------------------------------

-- file: fifostream.vhdl
-- content: first-in first-out stream 1 bit width
-- Created: 2024 august 12
-- Author: Roch Schanen
-- comments:
-- synchronous with the rising edge of trigger signal t
-- asynchronously cleared when reset signal r is low
-- generic size is any positive integer
-- size = 0 means that the pipe is a single wire      (index   0)
-- size = 1 means that the pipe is a single flip-flop (indices 0, 1)
-- size = N means a linked chain of N flip-flops      (indices 0, 1, etc...)

-------------
library ieee;
use ieee.std_logic_1164.all;

--------------------
entity fifostream is
    generic (size : integer := 0);  -- buffer size
    port (r : in  std_logic;        -- reset (active low)
          t : in  std_logic;        -- trigger (rising edge)
          i : in  std_logic;        -- data in
          -- output just the full buffer vector
          b : out std_logic_vector(size downto 0));
end entity fifostream;

---------------------------------------------
architecture fifostream_arch of fifostream is

    -- internal buffer
    signal bf: std_logic_vector(size downto 0);

begin
    
    -- the least significant bit (LSB)
    -- is always a copy of the input port
    bf(0) <= i;

    -- the full buffer is available at any time
    b <= bf;

    -----------------------------
    -- case N = 0
    -----------------------------

    -- the LSB is also the MSB,
    -- no extra hardware to generate

    -----------------------------
    -- case N > 0:
    -----------------------------

    NGATES : if size > 0 generate


    begin

        -- sequential logic
        process(r, t)
        begin
        
            -- asynchronous reset
            if r = '0' then
                
                -- clear internal buffer
                bf(size downto 1) <= (others => '0');

            -- synchronous shift
            elsif rising_edge(t) then
                
 
                --bf(4) <= bf(3);
                --bf(3) <= bf(2);
                --bf(2) <= bf(1);
                --bf(1) <= bf(0);
                
                -- the above code does NOT require
                -- the line "bf(0) <= i;" as I would
                -- expect, NOT like the code below.

                ---- shift stream bits
                for n in size downto 1 loop
                    bf(n) <= bf(n-1);
                end loop;

                -- next line required only when
                -- using the loop above. Why?
                bf(0) <= i;

            end if;

        end process;

    end generate NGATES;

end architecture fifostream_arch;

-------------------------------------------------------------------------------

bench/benchclock.vhdl
---------------------------------------------------------------------

-- file: benchclock.vhd
-- content: clock to be used by the fpga_bench
-- Created: 2024 july 28
-- Author: Roch Schanen
-- comments:
-- Simulate an external clock for the FPGA bench.
-- The clock alternates state between 0 and 1. It
-- waits HALF_PERIOD between states, and repeats
-- indefinitely (note that this is a purely virtual
-- device).

---------------------------------------------------------------------

-------------------------------------------------
--                BENCHCLOCK
-------------------------------------------------

library IEEE;
use IEEE.STD_LOGIC_1164.ALL;

entity benchclock is

    -- configure clock
    generic (HALF_PERIOD: time := 5 ns);

    -- only one output port
    Port ( o : out STD_LOGIC);

-- done
end benchclock;

architecture benchclock_arch of benchclock is

    -- define clock state
    signal s : STD_LOGIC := '0';

begin

    process

    begin

        -- repeat indefinitely
        while true loop

            -- set clock state high
            s <= '1';

            -- wait
            wait for HALF_PERIOD;

            -- set clock state low
            s <= '0';

            -- wait
            wait for HALF_PERIOD;

        -- and again
        end loop;

    end process;

    -- output the clock state
    o <= s;

-- done
end benchclock_arch;

benchreset.vhdl
---------------------------------------------------------------------

-- file: benchreset.vhdl
-- content: reset switch to be used by the fpga_bench
-- Created: 2024 july 28
-- Author: Roch Schanen
-- comments:
-- Simulate an external reset switch for the FPGA bench.
-- The reset start at a low level and rise after a fixed
-- PERIOD of time and remains high indefinitely (note that
-- this is a purely virtual device).

---------------------------------------------------------------------

-------------------------------------------------
--                BENCHRESET
-------------------------------------------------

library IEEE;
use IEEE.STD_LOGIC_1164.ALL;

entity benchreset is

    -- configure reset
    generic (PERIOD: time := 10 ns);

    -- only one output port
    Port ( o : out STD_LOGIC);

-- done
end benchreset;

architecture benchreset_arch of benchreset is

    -- define reset state
    --signal s : STD_LOGIC := '0';
    signal s : STD_LOGIC;

begin

    process

    begin

        wait for 1 ns;

        -- set reset state low
        s <= '0';

        -- wait
        wait for PERIOD;

        -- set reset state high
        s <= '1';

        -- wait forever
        wait;

    end process;

    -- output the reset state
    o <= s;

-- done
end benchreset_arch;

fifostream_bench.vhdl
-------------------------------------------------------------------------------

-- file: fifostream_bench.vhd
-- content: bench to simulate fifostream entity
-- Created: 2024 August 12
-- Author: Roch Schanen
-- comments:

-------------------------------------------------
--          FIFO STREAM BENCH
-------------------------------------------------

library IEEE;
use IEEE.STD_LOGIC_1164.ALL;

library work;
use work.all;

-------------------------------------------------

entity fifostream_bench is
end fifostream_bench;

-------------------------------------------------

architecture fifostream_bench_arch of fifostream_bench is

    -- configuration
    constant SIZE : integer := 4;

    -- signals
    signal r : std_logic;                       -- bench reset
    signal t : std_logic;                       -- bench clock
    signal q : std_logic_vector(SIZE downto 0); -- fifostream output

    signal test: std_logic;

begin

    -- instanciate bench reset
    bench_reset_1: entity benchreset
        generic map(3 ns)   -- duration
        port map(r);        -- r: reset signal

    -- instanciate bench clock
    bench_clock_1: entity benchclock
        generic map(2.5 ns) -- 200MHz
        port map(t);        -- t: clock signal

    -- instanciate fifo stream
    fifo_stream_1: entity fifostream
        generic map(SIZE)
        port map(r, t, test, q);

    process
    begin

        wait for 5 ns;
        test <= '0';

        wait for 7 ns;
        test <= '1';

        wait for 7 ns;
        test <= '0';

        wait for 7 ns;
        test <= '1';

        wait;

    end process;


end fifostream_bench_arch;

.outputs/bench.vcd
$date
  Tue Aug 13 05:18:00 2024
$end
$version
  GHDL v0
$end
$timescale
  1 fs
$end
$scope module standard $end
$upscope $end
$scope module std_logic_1164 $end
$upscope $end
$scope module fifostream_bench $end
$var reg 1 ! r $end
$var reg 1 " t $end
$var reg 5 # q[4:0] $end
$var reg 1 $ test $end
$scope module bench_reset_1 $end
$var reg 1 % o $end
$var reg 1 & s $end
$upscope $end
$scope module bench_clock_1 $end
$var reg 1 ' o $end
$var reg 1 ( s $end
$upscope $end
$scope module fifo_stream_1 $end
$var reg 1 ) r $end
$var reg 1 * t $end
$var reg 1 + i $end
$var reg 5 , b[4:0] $end
$var reg 5 - bf[4:0] $end
$scope module ngates $end
$upscope $end
$upscope $end
$upscope $end
$enddefinitions $end
#0
U!
1"
bUUUUU #
U$
U%
U&
1'
1(
U)
1*
U+
bUUUUU ,
bUUUUU -
#1000000
0!
b0000U #
0%
0&
0)
b0000U ,
b0000U -
#2500000
0"
0'
0(
0*
#4000000
1!
1%
1&
1)
#5000000
1"
b000U0 #
0$
1'
1(
1*
0+
b000U0 ,
b000U0 -
#7500000
0"
0'
0(
0*
#10000000
1"
b00U00 #
1'
1(
1*
b00U00 ,
b00U00 -
#12000000
b00U0X #
1$
1+
b00U0X ,
b00U0X -
#12500000
0"
0'
0(
0*
#15000000
1"
b0U0X1 #
1'
1(
1*
b0U0X1 ,
b0U0X1 -
#17500000
0"
0'
0(
0*
#19000000
b0U0XX #
0$
0+
b0U0XX ,
b0U0XX -
#20000000
1"
bU0XX0 #
1'
1(
1*
bU0XX0 ,
bU0XX0 -
#22500000
0"
0'
0(
0*
#25000000
1"
b0XX00 #
1'
1(
1*
b0XX00 ,
b0XX00 -
#26000000
b0XX0X #
1$
1+
b0XX0X ,
b0XX0X -
#27500000
0"
0'
0(
0*
#30000000
1"
bXX0X1 #
1'
1(
1*
bXX0X1 ,
bXX0X1 -
#32500000
0"
0'
0(
0*
#35000000
1"
bX0X11 #
1'
1(
1*
bX0X11 ,
bX0X11 -
#37500000
0"
0'
0(
0*
#40000000
1"
b0X111 #
1'
1(
1*
b0X111 ,
b0X111 -
#42500000
0"
0'
0(
0*
#45000000
1"
bX1111 #
1'
1(
1*
bX1111 ,
bX1111 -
#47500000
0"
0'
0(
0*
#50000000
1"
b11111 #
1'
1(
1*
b11111 ,
b11111 -
