plpr/fifostream.vhdl
-------------------------------------------------------------------------------
-- file: fifostream.vhdl
-- content: first-in first-out stream 1 bit width
-- Created: 2024 august 12
-- Author: Roch Schanen
-- comments:
-- synchronous with the rising edge of trigger signal t
-- asynchronously cleared when reset signal r is low
-- generic size is any positive integer
-- size = 0 means that the pipe is a single wire (1 index: 0)
-- size = 1 means that the pipe is a single flip-flop (2 indices: 0 and 1)
-- size = N means a linked chain of N flip-flops (N+1 indices 0, 1, up to N)
-- the ouput o(0) is a straight unbuffered copy of the input bit i
-- the other outputs are a copy of the current buffered stream: this
-- allows to pick up the same signal at the appropriate instant or delay

-------------
library ieee;
use ieee.std_logic_1164.all;

entity fifostream is
    generic (size : integer := 0);  -- buffer size
    port (r : in  std_logic;        -- reset (active low)
          t : in  std_logic;        -- trigger (rising edge)
          i : in  std_logic;        -- data in
          o : out std_logic_vector(size downto 0)); -- data out
end entity fifostream;

---------------------------------------------
architecture fifostream_arch of fifostream is
begin

    ---- always forward input bit to ouput port-0
    o(0) <= i;

    -- case N > 0:
    NGATES : if size > 0 generate

        -- buffer
        signal bf: std_logic_vector(size-1 downto 0);

    begin

        -- sequential logic
        process(r, t)
        begin

            -- asynchronous reset
            if r = '0' then

                -- clear buffer
                bf(size-1 downto 0) <= (others => '0');

            -- synchronous shift
            elsif rising_edge(t) then

                -- shift internal flip-flops
                for n in size-1 downto 1 loop
                    bf(n) <= bf(n-1);
                end loop;

                -- first flip-flop
                bf(0) <= i;

            end if;

        -- done
        end process;

        -- output buffered stream to port
        o(size downto 1) <= bf;

    -- done
    end generate NGATES;

-- done
end architecture fifostream_arch;

-------------------------------------------------------------------------------

plpr/plpr.vhdl
--------------------------------------------------------------------------------
-- file: plpr.vhdl
-- content: pipelined signed product
-- created: 2024 august 10
-- author: roch schanen
-- comments:
-- synchronous with the rising edge of trigger signal t
-- asynchronously cleared when reset signal r is low
-- generic size has been tested for integers larger than 4 <- only 4 so far
-- compute the product of two signed binary numbers, the result is signed
-- this version has redondant pipeline (pipelines running in parallel
-- that carry the exact same information)

-------------------------------------------------
--      PIPELINED SIGNED PRODUCT ARITHMETIC
-------------------------------------------------

library ieee;
use ieee.std_logic_1164.all;
use ieee.std_logic_arith.all;

library work;
use work.all;

--------------
entity plpr is
    generic (size : integer := 4);                      -- factors size
    port (r : in  std_logic;                            -- reset (active low)
          t : in  std_logic;                            -- trigger (rising edge)
          a : in  std_logic_vector(size-1 downto 0);    -- input a (4 bits)
          b : in  std_logic_vector(size-1 downto 0);    -- input b (4 bits)
          p : out std_logic_vector(2*size-1 downto 0)); -- product ab (8 bits)
end entity plpr;

---------------------------------
architecture plpr_arch of plpr is

    -------------------------------
    constant N0  : integer := size;    
    constant N1  : integer := size-1;
    constant N2  : integer := size-2;

    ---------------------------------
    constant NN0 : integer := 2*size;
    constant NN1 : integer := 2*size-1;
    constant NN2 : integer := 2*size-2;

    ---------------------------------------------------------------
    type type_1 is array (0 to N1,  0 to N1) of std_logic;
    type type_2 is array (0 to NN1, 0 to NN1) of std_logic;
    type type_3 is array (0 to N1,  0 to N1, 0 to 4*N0) of std_logic;

    ------------------------------------------------
    -- connections to the bit products (size x size)
    -- (the full square is used)
    signal pi: type_1;

    ---------------------------------------------------------
    -- connections to the add-sync entities (size x size x 4)
    -- (top-left triangle plus diagonal means a bit more than half are used)
    signal do, co: type_2;

    ------------------------------------------------------------
    -- connections to the input streams (size x size x size x 4)
    -- (only few connections are used, but a clean indexing is necessary)
    signal pp: type_3;

    -----------------------------------------
    -- data bit row n from cell position i, j
    function n(i: integer; j: integer) return integer is    
        variable x: integer;
    begin
        if j > 3 then x := 3; else x := j; end if;
        return x;
    end function;

    --------------------------------------------
    -- data bit column m from cell position i, j
    function m(i: integer; j: integer) return integer is    
        variable x: integer;
    begin
        if i-j < size then x := i-j; else x := 3; end if;
        return x;
    end function;

begin


    -- TEMP
    p <= (others => '0');

    ---------------
    -- BIT PRODUCTS
    ---------------
    subnet_a: for j in 0 to N1 generate
        subnet_b: for i in 0 to N1 generate
            pi(i,j) <= a(i) and b(j);
        end generate subnet_b;
    end generate subnet_a;

    ----------------
    -- INPUT STREAMS
    ----------------

    subnet_fifo_A: for j in NN1 downto N0 generate

        fifo_stream_mn: entity fifostream

            -- fifo length (i+j)
            generic map(NN1+j)

            -- sync signals
            port map(r, t,
                pi( -- bit product a(n) & b(m)
                    n(NN1, j),
                    m(NN1, j)),
                pp( -- reference signal n, m, k
                    n(NN1, j),
                    m(NN1, j),
                    NN1+j downto 0));

    end generate subnet_fifo_A;

    --subnet_fifo_B: for j in N1 downto 0 generate
    --    fifo_stream_mn: entity fifostream
    --        generic (NN1+j) -- fifo length (i+j)
    --        port map (r, t, -- sync signals
    --            pi( -- bit product a(n) & b(m)
    --                n(NN1, j),
    --                m(NN1, j)),
    --            pp( -- reference signal n, m, k
    --                n(NN1, j),
    --                m(NN1, j),
    --                NN1+j));
    --end generate subnet_fifo_B;

    --subnet_fifo_j: for j in 0 to size-1 generate
    --    subnet_fifo_i: for i in 0 to size-1 generate
    --    fifo_stream_mn: entity fifostream
    --        generic (NN1+j) -- fifo length (i+j)
    --        port map (r, t, -- sync signals
    --            pi( -- bit product a(n) & b(m)
    --                n(NN1, j),
    --                m(NN1, j)),
    --            pp( -- reference signal n, m, k
    --                n(NN1, j),
    --                m(NN1, j),
    --                NN1+j));
    --    end generate subnet_fifo_i;
    --end generate subnet_fifo_j;

    ------------------------------
    ---- TOP-RIGHT CELL (i=0, j=0)
    ------------------------------

    ---- instantiate input fifo buffer:
    --fifo_in_00: entity fifobuf
    --    generic map(0+0)            -- fifo length
    --    port map(r, t,              -- sync signals
    --        pi(n(0,0), m(0,0)),     -- input product a(n) & b(m)
    --        db(0,0));               -- output to cell 0,0

    ---- instantiate sync adder
    --async_00: entity addsync
    --    port map(r, t,              -- sync signals
    --        '0',                    -- input data A has no cell above
    --        db(0,0),                -- input data B from input buffer
    --        '0',                    -- carry in has no cell on the right
    --        do(0,0),                -- data  out
    --        co(0,0));               -- carry out

    ---- instantiate output fifo buffer
    --fifo_out_00: entity fifobuf
    --    generic map(2*(7-0))
    --    port map(r, t,              -- sync signals
    --        do(0,0),                -- input from last cell
    --        p(0));                  -- output to port

    -------------------
    ---- TOP LINE (j=0)
    -------------------
    --subnet_i0: for i in 1 to 7 generate

    --    -- instantiate input fifo buffer:
    --    fifo_in_i0: entity fifobuf
    --        generic map(i+0)        -- fifo length
    --        port map(r, t,          -- sync signals
    --            pi(n(i,0), m(i,0)), -- input product a(n) & b(m)
    --            db(i,0));           -- output to cell i,0

    --    -- instantiate sync adder
    --    async_i0: entity addsync
    --        port map(r, t,          -- sync signals
    --            '0',                -- input data A has no cell above
    --            db(i,0),            -- input data B from input buffer
    --            co(i-1,0),          -- carry in from cell on the right
    --            do(i,0),            -- data  out
    --            co(i,0));           -- carry out

    --end generate subnet_i0;

    -------------------------
    ---- UPPER TRIANGLE (i>j)
    -------------------------
    --subnet_j: for j in 1 to 7 generate
    --subnet_i: for i in 1 to 7 generate
    --upper_triangle: if i > j generate

    --    -- instantiate input fifo buffer:
    --    fifo_in_ij: entity fifobuf
    --        generic map(i+j)        -- fifo length
    --        port map(r, t,          -- sync signals
    --            pi(n(i,j), m(i,j)), -- input product a(n) & b(m)
    --            db(i,j));           -- output to cell i,j

    --    -- instantiate sync adder
    --    async_ij: entity addsync
    --        port map(r, t,  -- sync signals
    --            do(i, j-1), -- input data A from cell above
    --            db(i, j),   -- input data B from input buffer
    --            co(i-1, j), -- carry in from cell on the right
    --            do(i, j),   -- data  out
    --            co(i, j));  -- carry out

    --end generate upper_triangle;
    --end generate subnet_i;
    --end generate subnet_j;

    ----------------------
    ---- DIAGONALE (i = j)
    ----------------------
    --subnet_k: for k in 1 to 7 generate

    --    -- instantiate input fifo buffer:
    --    fifo_in_kk: entity fifobuf
    --        generic map(k+k)        -- fifo length
    --        port map(r, t,          -- sync signals
    --            pi(n(k,k), m(k,k)), -- input product a(n) & b(m)
    --            db(k,k));           -- output to cell k,k

    --    -- instantiate sync adder
    --    async_kk: entity addsync
    --        port map(r, t,  -- sync signals
    --            do(k, k-1), -- input data A from cell above
    --            db(k, k),   -- input data B from input buffer
    --            '0',        -- carry has no cell on the right
    --            do(k, k),   -- data  out
    --            co(k, k));  -- carry out

    --    -- instantiate output fifo buffer
    --    fifo_out_kk: entity fifobuf
    --        generic map(2*(7-k))
    --        port map(r, t,  -- sync signals
    --            do(k,k),    -- input from last cell
    --            p(k));      -- output to port

    --end generate subnet_k;

end architecture plpr_arch;

-------------------------------------------------

bench/benchcounter.vhdl
---------------------------------------------------------------------

-- file: benchcounter.vhd
-- content: generic counter
-- Created: 2024 august 08
-- Author: Roch Schanen
-- comments:
-- generic counter device for the FPGA bench,
-- with a rising edge triggered clock input,
-- and aa asynchronous reset. The size of the
-- counter is configurable. The intial counter
-- state is not initialised (use reset).

---------------------------------------------------------------------

-------------------------------------------------
--                BENCH CLOCK
-------------------------------------------------

library IEEE;
use IEEE.STD_LOGIC_1164.ALL;
use IEEE.NUMERIC_STD.all;

-------------------------------------------------

entity benchcounter is

    -- configure clock
    generic (SIZE: integer := 8);

    -- only one output port
    Port (
        r : in  std_logic;                              -- asynchronous reset
        t : in  std_logic;                              -- egded triggered clock
        c : out std_logic_vector (SIZE-1 downto 0));    -- counter state

-- done
end benchcounter;

-------------------------------------------------

architecture benchcounter_arch of benchcounter is
    -- define reset counter state
    constant z : std_logic_vector(SIZE-1 downto 0) := (others => '0');
    -- define counter state
    signal s : std_logic_vector (SIZE-1 downto 0);

begin

    -- sequential logic
    process(r, t)

    begin

        -- asynchronous reset
        if r = '0' then
            s <= z;

        -- rising edge triggered count
        elsif rising_edge(t) then
            s <= std_logic_vector(unsigned(s)+1);

        end if;

    end process;

    -- output counter value
    c <= s;

-- done
end benchcounter_arch;

-------------------------------------------------

benchreset.vhdl
---------------------------------------------------------------------

-- file: benchreset.vhdl
-- content: reset switch to be used by the fpga_bench
-- Created: 2024 july 28
-- Author: Roch Schanen
-- comments:
-- Simulate an external reset switch for the FPGA bench.
-- The reset start at a low level and rise after a fixed
-- PERIOD of time and remains high indefinitely (note that
-- this is a purely virtual device).

---------------------------------------------------------------------

-------------------------------------------------
--                BENCHRESET
-------------------------------------------------

library IEEE;
use IEEE.STD_LOGIC_1164.ALL;

entity benchreset is

    -- configure reset
    generic (PERIOD: time := 10 ns);

    -- only one output port
    Port ( o : out STD_LOGIC);

-- done
end benchreset;

architecture benchreset_arch of benchreset is

    -- define reset state
    --signal s : STD_LOGIC := '0';
    signal s : STD_LOGIC;

begin

    process

    begin

        wait for 1 ns;

        -- set reset state low
        s <= '0';

        -- wait
        wait for PERIOD;

        -- set reset state high
        s <= '1';

        -- wait forever
        wait;

    end process;

    -- output the reset state
    o <= s;

-- done
end benchreset_arch;

bench/benchclock.vhdl
---------------------------------------------------------------------

-- file: benchclock.vhd
-- content: clock to be used by the fpga_bench
-- Created: 2024 july 28
-- Author: Roch Schanen
-- comments:
-- Simulate an external clock for the FPGA bench.
-- The clock alternates state between 0 and 1. It
-- waits HALF_PERIOD between states, and repeats
-- indefinitely (note that this is a purely virtual
-- device).

---------------------------------------------------------------------

-------------------------------------------------
--                BENCHCLOCK
-------------------------------------------------

library IEEE;
use IEEE.STD_LOGIC_1164.ALL;

entity benchclock is

    -- configure clock
    generic (HALF_PERIOD: time := 5 ns);

    -- only one output port
    Port ( o : out STD_LOGIC);

-- done
end benchclock;

architecture benchclock_arch of benchclock is

    -- define clock state
    signal s : STD_LOGIC := '0';

begin

    process

    begin

        -- repeat indefinitely
        while true loop

            -- set clock state high
            s <= '1';

            -- wait
            wait for HALF_PERIOD;

            -- set clock state low
            s <= '0';

            -- wait
            wait for HALF_PERIOD;

        -- and again
        end loop;

    end process;

    -- output the clock state
    o <= s;

-- done
end benchclock_arch;

plpr_bench.vhdl
---------------------------------------------------------------------

-- file: plpr_bench.vhd
-- content: bench to simulate plpr code
-- Created: 2024 August 4
-- Author: Roch Schanen
-- comments:

---------------------------------------------------------------------

-------------------------------------------------
--          PIPELINED PRODUCT BENCH
-------------------------------------------------

library IEEE;
use IEEE.STD_LOGIC_1164.ALL;

use IEEE.STD_LOGIC_ARITH.ALL;
use IEEE.STD_LOGIC_UNSIGNED.ALL;

library work;
use work.all;

-------------------------------------------------

entity plpr_bench is
end plpr_bench;

-------------------------------------------------

architecture plpr_bench_arch of plpr_bench is

    -- configuration

    constant SIZE : integer := 4;

    -- signals
    signal r : std_logic;                           -- bench reset
    signal t : std_logic;                           -- bench clock
    signal c : std_logic_vector(2*SIZE-1 downto 0); -- bench counter
    signal a : std_logic_vector(SIZE-1 downto 0);
    signal b : std_logic_vector(SIZE-1 downto 0);

    signal q : std_logic_vector(2*SIZE-1 downto 0); -- plpr output

    -- display function (variable size logic vector)
    function to_string(v :std_logic_vector)
        return string is variable s : string(v'length downto 1);
    begin
        for i in v'range loop
            if v(i) = '1' then
                s(i+1) := '1';
            else
                s(i+1) := '0';
            end if;
        end loop;
        return s;
    end function;

begin

    -- instanciate bench clock
    bench_clock_1: entity benchclock
        generic map(2.5 ns) -- 200MHz
        port map(t);        -- t: clock signal

    -- instanciate bench reset
    bench_reset_1: entity benchreset
        generic map(3 ns)   -- duration
        port map(r);        -- r: reset signal

    -- instanciate bench counter
    bench_counter_1: entity benchcounter
        generic map(2*SIZE) -- counter size
        port map(r, t, c);  -- a: counter output

    -- extract subsets
    a <= c(3 downto 0);
    b <= c(7 downto 4);

    -- instanciate pipelined nco
    pl_pr_1: entity plpr
        generic map(SIZE)
        port map(r, t, a, b, q);    -- scan through all

    -- --synchronised reporting (use file outputs instead for cleaner testing)
    --process(r, t) is
    --begin
    --    if rising_edge(t) then
    --        report to_string(a) & "x" & to_string(b) & "=" & to_string(q) ;
    --    end if;
    --end process;

end plpr_bench_arch;

-------------------------------------------------

.outputs/bench.vcd
$date
  Tue Aug 13 20:34:38 2024
$end
$version
  GHDL v0
$end
$timescale
  1 fs
$end
$scope module standard $end
$upscope $end
$scope module std_logic_1164 $end
$upscope $end
$scope module std_logic_arith $end
$upscope $end
$scope module std_logic_unsigned $end
$upscope $end
$scope module numeric_std $end
$upscope $end
$scope module plpr_bench $end
$var reg 1 ! r $end
$var reg 1 " t $end
$var reg 8 # c[7:0] $end
$var reg 4 $ a[3:0] $end
$var reg 4 % b[3:0] $end
$var reg 8 & q[7:0] $end
$scope module bench_clock_1 $end
$var reg 1 ' o $end
$var reg 1 ( s $end
$upscope $end
$scope module bench_reset_1 $end
$var reg 1 ) o $end
$var reg 1 * s $end
$upscope $end
$scope module bench_counter_1 $end
$var reg 1 + r $end
$var reg 1 , t $end
$var reg 8 - c[7:0] $end
$var reg 8 . s[7:0] $end
$upscope $end
$scope module pl_pr_1 $end
$var reg 1 / r $end
$var reg 1 0 t $end
$var reg 4 1 a[3:0] $end
$var reg 4 2 b[3:0] $end
$var reg 8 3 p[7:0] $end
$comment pi is not handled $end
$comment do is not handled $end
$comment co is not handled $end
$comment pp is not handled $end
$scope module subnet_a(0) $end
$scope module subnet_b(0) $end
$upscope $end
$scope module subnet_b(1) $end
$upscope $end
$scope module subnet_b(2) $end
$upscope $end
$scope module subnet_b(3) $end
$upscope $end
$upscope $end
$scope module subnet_a(1) $end
$scope module subnet_b(0) $end
$upscope $end
$scope module subnet_b(1) $end
$upscope $end
$scope module subnet_b(2) $end
$upscope $end
$scope module subnet_b(3) $end
$upscope $end
$upscope $end
$scope module subnet_a(2) $end
$scope module subnet_b(0) $end
$upscope $end
$scope module subnet_b(1) $end
$upscope $end
$scope module subnet_b(2) $end
$upscope $end
$scope module subnet_b(3) $end
$upscope $end
$upscope $end
$scope module subnet_a(3) $end
$scope module subnet_b(0) $end
$upscope $end
$scope module subnet_b(1) $end
$upscope $end
$scope module subnet_b(2) $end
$upscope $end
$scope module subnet_b(3) $end
$upscope $end
$upscope $end
$upscope $end
$upscope $end
$enddefinitions $end
#0
U!
1"
bXXXXXXXX #
bXXXX $
bXXXX %
b00000000 &
1'
1(
U)
U*
U+
1,
bXXXXXXXX -
bXXXXXXXX .
U/
10
bXXXX 1
bXXXX 2
b00000000 3
#1000000
0!
b00000000 #
b0000 $
b0000 %
0)
0*
0+
b00000000 -
b00000000 .
0/
b0000 1
b0000 2
#2500000
0"
0'
0(
0,
00
#4000000
1!
1)
1*
1+
1/
#5000000
1"
b00000001 #
b0001 $
1'
1(
1,
b00000001 -
b00000001 .
10
b0001 1
#7500000
0"
0'
0(
0,
00
#10000000
1"
b00000010 #
b0010 $
1'
1(
1,
b00000010 -
b00000010 .
10
b0010 1
#12500000
0"
0'
0(
0,
00
#15000000
1"
b00000011 #
b0011 $
1'
1(
1,
b00000011 -
b00000011 .
10
b0011 1
#17500000
0"
0'
0(
0,
00
#20000000
1"
b00000100 #
b0100 $
1'
1(
1,
b00000100 -
b00000100 .
10
b0100 1
#22500000
0"
0'
0(
0,
00
#25000000
1"
b00000101 #
b0101 $
1'
1(
1,
b00000101 -
b00000101 .
10
b0101 1
#27500000
0"
0'
0(
0,
00
#30000000
1"
b00000110 #
b0110 $
1'
1(
1,
b00000110 -
b00000110 .
10
b0110 1
#32500000
0"
0'
0(
0,
00
#35000000
1"
b00000111 #
b0111 $
1'
1(
1,
b00000111 -
b00000111 .
10
b0111 1
#37500000
0"
0'
0(
0,
00
#40000000
1"
b00001000 #
b1000 $
1'
1(
1,
b00001000 -
b00001000 .
10
b1000 1
#42500000
0"
0'
0(
0,
00
#45000000
1"
b00001001 #
b1001 $
1'
1(
1,
b00001001 -
b00001001 .
10
b1001 1
#47500000
0"
0'
0(
0,
00
#50000000
1"
b00001010 #
b1010 $
1'
1(
1,
b00001010 -
b00001010 .
10
b1010 1
#52500000
0"
0'
0(
0,
00
#55000000
1"
b00001011 #
b1011 $
1'
1(
1,
b00001011 -
b00001011 .
10
b1011 1
#57500000
0"
0'
0(
0,
00
#60000000
1"
b00001100 #
b1100 $
1'
1(
1,
b00001100 -
b00001100 .
10
b1100 1
#62500000
0"
0'
0(
0,
00
#65000000
1"
b00001101 #
b1101 $
1'
1(
1,
b00001101 -
b00001101 .
10
b1101 1
#67500000
0"
0'
0(
0,
00
#70000000
1"
b00001110 #
b1110 $
1'
1(
1,
b00001110 -
b00001110 .
10
b1110 1
#72500000
0"
0'
0(
0,
00
#75000000
1"
b00001111 #
b1111 $
1'
1(
1,
b00001111 -
b00001111 .
10
b1111 1
#77500000
0"
0'
0(
0,
00
#80000000
1"
b00010000 #
b0000 $
b0001 %
1'
1(
1,
b00010000 -
b00010000 .
10
b0000 1
b0001 2
#82500000
0"
0'
0(
0,
00
#85000000
1"
b00010001 #
b0001 $
1'
1(
1,
b00010001 -
b00010001 .
10
b0001 1
#87500000
0"
0'
0(
0,
00
#90000000
1"
b00010010 #
b0010 $
1'
1(
1,
b00010010 -
b00010010 .
10
b0010 1
#92500000
0"
0'
0(
0,
00
#95000000
1"
b00010011 #
b0011 $
1'
1(
1,
b00010011 -
b00010011 .
10
b0011 1
#97500000
0"
0'
0(
0,
00
#100000000
1"
b00010100 #
b0100 $
1'
1(
1,
b00010100 -
b00010100 .
10
b0100 1
#102500000
0"
0'
0(
0,
00
#105000000
1"
b00010101 #
b0101 $
1'
1(
1,
b00010101 -
b00010101 .
10
b0101 1
#107500000
0"
0'
0(
0,
00
#110000000
1"
b00010110 #
b0110 $
1'
1(
1,
b00010110 -
b00010110 .
10
b0110 1
#112500000
0"
0'
0(
0,
00
#115000000
1"
b00010111 #
b0111 $
1'
1(
1,
b00010111 -
b00010111 .
10
b0111 1
#117500000
0"
0'
0(
0,
00
#120000000
1"
b00011000 #
b1000 $
1'
1(
1,
b00011000 -
b00011000 .
10
b1000 1
#122500000
0"
0'
0(
0,
00
#125000000
1"
b00011001 #
b1001 $
1'
1(
1,
b00011001 -
b00011001 .
10
b1001 1
#127500000
0"
0'
0(
0,
00
#130000000
1"
b00011010 #
b1010 $
1'
1(
1,
b00011010 -
b00011010 .
10
b1010 1
#132500000
0"
0'
0(
0,
00
#135000000
1"
b00011011 #
b1011 $
1'
1(
1,
b00011011 -
b00011011 .
10
b1011 1
#137500000
0"
0'
0(
0,
00
#140000000
1"
b00011100 #
b1100 $
1'
1(
1,
b00011100 -
b00011100 .
10
b1100 1
#142500000
0"
0'
0(
0,
00
#145000000
1"
b00011101 #
b1101 $
1'
1(
1,
b00011101 -
b00011101 .
10
b1101 1
#147500000
0"
0'
0(
0,
00
#150000000
1"
b00011110 #
b1110 $
1'
1(
1,
b00011110 -
b00011110 .
10
b1110 1
#152500000
0"
0'
0(
0,
00
#155000000
1"
b00011111 #
b1111 $
1'
1(
1,
b00011111 -
b00011111 .
10
b1111 1
#157500000
0"
0'
0(
0,
00
#160000000
1"
b00100000 #
b0000 $
b0010 %
1'
1(
1,
b00100000 -
b00100000 .
10
b0000 1
b0010 2
#162500000
0"
0'
0(
0,
00
#165000000
1"
b00100001 #
b0001 $
1'
1(
1,
b00100001 -
b00100001 .
10
b0001 1
#167500000
0"
0'
0(
0,
00
#170000000
1"
b00100010 #
b0010 $
1'
1(
1,
b00100010 -
b00100010 .
10
b0010 1
#172500000
0"
0'
0(
0,
00
#175000000
1"
b00100011 #
b0011 $
1'
1(
1,
b00100011 -
b00100011 .
10
b0011 1
#177500000
0"
0'
0(
0,
00
#180000000
1"
b00100100 #
b0100 $
1'
1(
1,
b00100100 -
b00100100 .
10
b0100 1
#182500000
0"
0'
0(
0,
00
#185000000
1"
b00100101 #
b0101 $
1'
1(
1,
b00100101 -
b00100101 .
10
b0101 1
#187500000
0"
0'
0(
0,
00
#190000000
1"
b00100110 #
b0110 $
1'
1(
1,
b00100110 -
b00100110 .
10
b0110 1
#192500000
0"
0'
0(
0,
00
#195000000
1"
b00100111 #
b0111 $
1'
1(
1,
b00100111 -
b00100111 .
10
b0111 1
#197500000
0"
0'
0(
0,
00
#200000000
1"
b00101000 #
b1000 $
1'
1(
1,
b00101000 -
b00101000 .
10
b1000 1
#202500000
0"
0'
0(
0,
00
#205000000
1"
b00101001 #
b1001 $
1'
1(
1,
b00101001 -
b00101001 .
10
b1001 1
#207500000
0"
0'
0(
0,
00
#210000000
1"
b00101010 #
b1010 $
1'
1(
1,
b00101010 -
b00101010 .
10
b1010 1
#212500000
0"
0'
0(
0,
00
#215000000
1"
b00101011 #
b1011 $
1'
1(
1,
b00101011 -
b00101011 .
10
b1011 1
#217500000
0"
0'
0(
0,
00
#220000000
1"
b00101100 #
b1100 $
1'
1(
1,
b00101100 -
b00101100 .
10
b1100 1
#222500000
0"
0'
0(
0,
00
#225000000
1"
b00101101 #
b1101 $
1'
1(
1,
b00101101 -
b00101101 .
10
b1101 1
#227500000
0"
0'
0(
0,
00
#230000000
1"
b00101110 #
b1110 $
1'
1(
1,
b00101110 -
b00101110 .
10
b1110 1
#232500000
0"
0'
0(
0,
00
#235000000
1"
b00101111 #
b1111 $
1'
1(
1,
b00101111 -
b00101111 .
10
b1111 1
#237500000
0"
0'
0(
0,
00
#240000000
1"
b00110000 #
b0000 $
b0011 %
1'
1(
1,
b00110000 -
b00110000 .
10
b0000 1
b0011 2
#242500000
0"
0'
0(
0,
00
#245000000
1"
b00110001 #
b0001 $
1'
1(
1,
b00110001 -
b00110001 .
10
b0001 1
#247500000
0"
0'
0(
0,
00
#250000000
1"
b00110010 #
b0010 $
1'
1(
1,
b00110010 -
b00110010 .
10
b0010 1
#252500000
0"
0'
0(
0,
00
#255000000
1"
b00110011 #
b0011 $
1'
1(
1,
b00110011 -
b00110011 .
10
b0011 1
#257500000
0"
0'
0(
0,
00
#260000000
1"
b00110100 #
b0100 $
1'
1(
1,
b00110100 -
b00110100 .
10
b0100 1
#262500000
0"
0'
0(
0,
00
#265000000
1"
b00110101 #
b0101 $
1'
1(
1,
b00110101 -
b00110101 .
10
b0101 1
#267500000
0"
0'
0(
0,
00
#270000000
1"
b00110110 #
b0110 $
1'
1(
1,
b00110110 -
b00110110 .
10
b0110 1
#272500000
0"
0'
0(
0,
00
#275000000
1"
b00110111 #
b0111 $
1'
1(
1,
b00110111 -
b00110111 .
10
b0111 1
#277500000
0"
0'
0(
0,
00
#280000000
1"
b00111000 #
b1000 $
1'
1(
1,
b00111000 -
b00111000 .
10
b1000 1
#282500000
0"
0'
0(
0,
00
#285000000
1"
b00111001 #
b1001 $
1'
1(
1,
b00111001 -
b00111001 .
10
b1001 1
#287500000
0"
0'
0(
0,
00
#290000000
1"
b00111010 #
b1010 $
1'
1(
1,
b00111010 -
b00111010 .
10
b1010 1
#292500000
0"
0'
0(
0,
00
#295000000
1"
b00111011 #
b1011 $
1'
1(
1,
b00111011 -
b00111011 .
10
b1011 1
#297500000
0"
0'
0(
0,
00
#300000000
1"
b00111100 #
b1100 $
1'
1(
1,
b00111100 -
b00111100 .
10
b1100 1
